ros_api/__init__.py
ros_api/_log.py
ros_api/api.py
laiarturs_ros_api-1.1.0.dist-info/LICENSE
laiarturs_ros_api-1.1.0.dist-info/METADATA
laiarturs_ros_api-1.1.0.dist-info/WHEEL
laiarturs_ros_api-1.1.0.dist-info/top_level.txt
laiarturs_ros_api-1.1.0.dist-info/RECORD
