Metadata-Version: 2.1
Name: laiarturs-ros-api
Version: 1.1.0
Summary: Connect to and use API interface of MikroTik RouterOS
Author: Arturs Laizans
License: MIT License
Project-URL: Homepage, https://github.com/DEssMALA/RouterOS_API
Keywords: MikroTik,RouterOS,router,API
Classifier: License :: OSI Approved :: MIT License
Classifier: Programming Language :: Python
Classifier: Programming Language :: Python :: 3
Classifier: Development Status :: 4 - Beta
Classifier: Topic :: System :: Networking
Requires-Python: >=3.4
Provides-Extra: dev
License-File: LICENSE
